{"appleSKU":"","appleTeamID":"","enableCodelessAutoInitialization":true,"enableUnityGamingServicesAutoInitialization":true,"products":[{"id":"com.chaloapps.roosterrudy.500coins","type":0,"storeIDs":[],"defaultDescription":{"googleLocale":4,"title":"500 coins","description":"500coins"},"screenshotPath":"","applePriceTier":1,"googlePrice":{"data":[0,0,0,0],"num":0.0},"pricingTemplateID":"","descriptions":[],"udpPrice":{"data":[0,0,0,0],"num":0.0},"payouts":[]},{"id":"com.chaloapps.roosterrudy.2000coins","type":0,"storeIDs":[],"defaultDescription":{"googleLocale":4,"title":"2000 coins","description":"2000coins"},"screenshotPath":"","applePriceTier":0,"googlePrice":{"data":[0,0,0,0],"num":0.0},"pricingTemplateID":"","descriptions":[],"udpPrice":{"data":[0,0,0,0],"num":0.0},"payouts":[]},{"id":"com.chaloapps.roosterrudy.10000coins","type":0,"storeIDs":[],"defaultDescription":{"googleLocale":4,"title":"10000 coins","description":"10000coins"},"screenshotPath":"","applePriceTier":0,"googlePrice":{"data":[0,0,0,0],"num":0.0},"pricingTemplateID":"","descriptions":[],"udpPrice":{"data":[0,0,0,0],"num":0.0},"payouts":[]},{"id":"com.chaloapps.roosterrudy.1000000coins","type":0,"storeIDs":[],"defaultDescription":{"googleLocale":4,"title":"1000000 coins","description":"1000000coins"},"screenshotPath":"","applePriceTier":0,"googlePrice":{"data":[0,0,0,0],"num":0.0},"pricingTemplateID":"","descriptions":[],"udpPrice":{"data":[0,0,0,0],"num":0.0},"payouts":[]}]}